odoo/addons/base_facturx/README.rst
odoo/addons/base_facturx/__init__.py
odoo/addons/base_facturx/__manifest__.py
odoo/addons/base_facturx/data/zugferd_codes.xml
odoo/addons/base_facturx/i18n/base_facturx.pot
odoo/addons/base_facturx/i18n/base_zugferd.pot
odoo/addons/base_facturx/i18n/es.po
odoo/addons/base_facturx/i18n/fr.po
odoo/addons/base_facturx/models/__init__.py
odoo/addons/base_facturx/models/base_facturx.py
odoo/addons/base_facturx/readme/CONFIGURE.rst
odoo/addons/base_facturx/readme/CONTRIBUTORS.rst
odoo/addons/base_facturx/readme/DESCRIPTION.rst
odoo/addons/base_facturx/readme/USAGE.rst
odoo/addons/base_facturx/static/description/icon.png
odoo/addons/base_facturx/static/description/index.html
odoo13_addon_base_facturx-13.0.1.0.1.dev7.dist-info/METADATA
odoo13_addon_base_facturx-13.0.1.0.1.dev7.dist-info/WHEEL
odoo13_addon_base_facturx-13.0.1.0.1.dev7.dist-info/top_level.txt
odoo13_addon_base_facturx-13.0.1.0.1.dev7.dist-info/RECORD
