Metadata-Version: 2.1
Name: odoo13-addon-base_facturx
Version: 13.0.1.0.1.dev7
Summary: Base module for Factur-X/ZUGFeRD
Home-page: https://github.com/OCA/edi
Author: Akretion,Odoo Community Association (OCA)
Author-email: support@odoo-community.org
License: AGPL-3
Classifier: Programming Language :: Python
Classifier: Framework :: Odoo
Classifier: Framework :: Odoo :: 13.0
Classifier: License :: OSI Approved :: GNU Affero General Public License v3
Requires-Python: >=3.5
Requires-Dist: odoo13-addon-account-payment-unece
Requires-Dist: odoo13-addon-account-tax-unece
Requires-Dist: odoo13-addon-uom-unece
Requires-Dist: odoo<13.1dev,>=13.0a
